tonescript/__init__.py
tonescript/_parser.py
tonescript/_wave.py
tonescript/audio.py
tonescript/model.py
tonescript/tonescript.lark
tonescript-1.0.0.dist-info/LICENSE.md
tonescript-1.0.0.dist-info/WHEEL
tonescript-1.0.0.dist-info/METADATA
tonescript-1.0.0.dist-info/RECORD
