Metadata-Version: 2.1
Name: tonescript
Version: 1.0.0
Summary: Python package for working with ToneScript, a syntax for describing the characteristics of the call progress tones used in telephony.
Home-page: https://github.com/gdereese/tonescript
License: MIT
Keywords: parser,telephony,tonescript
Author: Gary DeReese
Author-email: garydereese@sbcglobal.net
Requires-Python: >=3.8,<4.0
Classifier: License :: OSI Approved :: MIT License
Classifier: Programming Language :: Python :: 3
Classifier: Programming Language :: Python :: 3.8
Classifier: Programming Language :: Python :: 3.9
Requires-Dist: lark (>=0.11.3,<0.12.0)
Project-URL: Issues, https://github.com/gdereese/tonescript/issues
Project-URL: Repository, https://github.com/gdereese/tonescript
